proxy_file_parser/__init__.py
proxy_file_parser/async_parser.py
proxy_file_parser/core.py
proxy_file_parser/sync_parser.py
proxy_file_parser-0.0.3.dist-info/licenses/LICENSE
proxy_file_parser-0.0.3.dist-info/METADATA
proxy_file_parser-0.0.3.dist-info/WHEEL
proxy_file_parser-0.0.3.dist-info/top_level.txt
proxy_file_parser-0.0.3.dist-info/RECORD
