Metadata-Version: 2.4
Name: proxy-file-parser
Version: 0.0.3
Summary: Библиотека для парсинга различных форматов прокси из файла
Author-email: Limby <bogo44tor@gmail.com>
License-Expression: MIT
Project-URL: Homepage, https://github.com/Limby-TH/proxy-file-parser
Project-URL: Repository, https://github.com/Limby-TH/proxy-file-parser
Project-URL: Bug Tracker, https://github.com/Limby-TH/proxy-file-parser/issues
Keywords: proxy,parser,network,socks,http,file
Classifier: Development Status :: 3 - Alpha
Classifier: Intended Audience :: Developers
Classifier: Programming Language :: Python :: 3
Classifier: Programming Language :: Python :: 3.8
Classifier: Programming Language :: Python :: 3.9
Classifier: Programming Language :: Python :: 3.10
Classifier: Programming Language :: Python :: 3.11
Classifier: Programming Language :: Python :: 3.12
Classifier: Operating System :: OS Independent
Classifier: Topic :: Internet :: Proxy Servers
Classifier: Topic :: Software Development :: Libraries :: Python Modules
Requires-Python: >=3.8
License-File: LICENSE
Requires-Dist: aiofiles>=0.8.0
Provides-Extra: dev
Requires-Dist: pytest>=6.0; extra == "dev"
Requires-Dist: pytest-asyncio; extra == "dev"
Requires-Dist: black; extra == "dev"
Requires-Dist: isort; extra == "dev"
Requires-Dist: mypy; extra == "dev"
Requires-Dist: flake8; extra == "dev"
Dynamic: license-file
